testAuth/__init__.py
testAuth/custom_handlers.py
libpiptest-1.0.0.dist-info/METADATA
libpiptest-1.0.0.dist-info/WHEEL
libpiptest-1.0.0.dist-info/top_level.txt
libpiptest-1.0.0.dist-info/RECORD
